speech_text_pipeline/__init__.py
speech_text_pipeline/main.py
speech_text_pipeline-0.1.3.dist-info/LICENSE
speech_text_pipeline-0.1.3.dist-info/METADATA
speech_text_pipeline-0.1.3.dist-info/WHEEL
speech_text_pipeline-0.1.3.dist-info/top_level.txt
speech_text_pipeline-0.1.3.dist-info/RECORD
