Metadata-Version: 2.1
Name: speech_text_pipeline
Version: 0.1.3
Summary: A Python package for speech transcription and speaker diarization with speaker matching functionality.
Author-email: Arya Shukla <aryashukla95@gmail.com>
License: Apache-2.0
Project-URL: Repository, https://github.com/aryashukla/speech_text_pipeline
Project-URL: Documentation, https://github.com/aryashukla/speech_text_pipeline/blob/main/README.md
Project-URL: Issue_Tracker, https://github.com/aryashukla/speech_text_pipeline/issues
Keywords: speech,text,diarization,speaker matching,NLP,openai-whisper,nvidia nemo
Classifier: Programming Language :: Python :: 3
Classifier: License :: OSI Approved :: Apache Software License
Classifier: Operating System :: OS Independent
Classifier: Intended Audience :: Developers
Classifier: Topic :: Software Development :: Libraries
Classifier: Topic :: Multimedia :: Sound/Audio
Requires-Python: >=3.10
License-File: LICENSE
Requires-Dist: transformers ==4.44.2
Requires-Dist: numpy ==1.26.4
Requires-Dist: scipy ==1.13.1
Requires-Dist: librosa ==0.10.2.post1
Requires-Dist: lhotse ==1.27.0
Requires-Dist: jiwer ==3.0.4
Requires-Dist: wget ==3.2
Requires-Dist: webdataset ==0.2.100
Requires-Dist: soundfile ==0.12.1
Requires-Dist: ipython ==7.34.0
Requires-Dist: ipython-genutils ==0.2.0
Requires-Dist: ipython-sql ==0.5.0
Requires-Dist: triton ==3.0.0
Requires-Dist: nvidia-cublas-cu11
Requires-Dist: nvidia-cuda-cupti-cu11
Requires-Dist: nvidia-cuda-nvrtc-cu11
Requires-Dist: nvidia-cuda-runtime-cu11
Requires-Dist: nvidia-cudnn-cu11
